testsuv/__init__.py
testsuv/cli.py
testsuv-0.1.0.dist-info/WHEEL
testsuv-0.1.0.dist-info/entry_points.txt
testsuv-0.1.0.dist-info/METADATA
testsuv-0.1.0.dist-info/RECORD
