Metadata-Version: 2.3
Name: testsuv
Version: 0.1.0
Summary: Add your description here
Author-email: cv0028101@gamil.com
Requires-Dist: httpx>=0.28.1
Requires-Dist: typer>=0.19.2
Requires-Python: >=3.12
